MANIFEST.in
README.rst
setup.py
core_nav/__init__.py
core_nav/apps.py
core_nav/forms.py
core_nav/urls.py
core_nav/views.py
core_nav/templates/core_nav/about.html
core_nav/templates/core_nav/choose-signup-option.html
core_nav/templates/core_nav/get-started.html
core_nav/templates/core_nav/home-360.html
core_nav/templates/core_nav/home-lens.html
core_nav/templates/core_nav/home.html
core_nav/templates/core_nav/overview-help.html
core_nav/templates/core_nav/school-code.html
core_nav/templates/core_nav/school-details.html
core_nav/templates/core_nav/settings.html
core_nav/templates/core_nav/user-details.html
django_core_nav_hashtag_learning.egg-info/PKG-INFO
django_core_nav_hashtag_learning.egg-info/SOURCES.txt
django_core_nav_hashtag_learning.egg-info/dependency_links.txt
django_core_nav_hashtag_learning.egg-info/top_level.txt